{
  "status": "success",
  "data": [
    {
      "location": "A0101101",
      "productId": "A1",
      "time": "09:10:20"
    },
    {
      "location": "A0101201",
      "productId": "A2",
      "time": "09:12:30"
    },
    {
      "location": "A0101301",
      "productId": "A3",
      "time": "09:15:25"
    },
    {
      "location": "A0101301",
      "productId": "A4",
      "time": "09:15:25"
    },
    {
      "location": "A0101202",
      "productId": "B1",
      "time": "09:15:25"
    },
    {
      "location": "A0101302",
      "productId": "B2",
      "time": "09:15:25"
    }
  ]
}